p_chat_to_excel/__init__.py
p_chat_to_excel/p_chat_to_excel.py
p_chat_to_excel-22.0.dist-info/METADATA
p_chat_to_excel-22.0.dist-info/WHEEL
p_chat_to_excel-22.0.dist-info/top_level.txt
p_chat_to_excel-22.0.dist-info/RECORD
