Metadata-Version: 2.1
Name: p_chat_to_excel
Version: 22.0
Summary: EZ way for api calling
Home-page: https://github.com/PennyXu/api_call
Author: XuPeng
Author-email: xupeng23456@126.com
License: MIT
Classifier: License :: OSI Approved :: MIT License
Classifier: Programming Language :: Python
Classifier: Programming Language :: Python :: 3
Classifier: Programming Language :: Python :: 3.6
Classifier: Programming Language :: Python :: Implementation :: CPython
Classifier: Programming Language :: Python :: Implementation :: PyPy
Requires-Python: >=3.9.0
Requires-Dist: openai
Requires-Dist: pandas
Requires-Dist: tqdm
Requires-Dist: numpy
Requires-Dist: langchain-text-splitters
Requires-Dist: sentence-transformers
Requires-Dist: PyPDF2
